LICENSE.md
MANIFEST.in
README.md
setup.cfg
setup.py
v2d/__init__.py
v2d/domains.py
v2d/main.py
v2d.egg-info/PKG-INFO
v2d.egg-info/SOURCES.txt
v2d.egg-info/dependency_links.txt
v2d.egg-info/entry_points.txt
v2d.egg-info/requires.txt
v2d.egg-info/top_level.txt
v2d/utils/__init__.py
v2d/utils/files.py
v2d/utils/images.py
v2d/utils/printing.py
v2d/utils/similarity.py
v2d/utils/unicode.py