Metadata-Version: 2.1
Name: v2d
Version: 0.0.1
Summary: v2d - cli generates new variations of an input based on similarity matrix generated by v2d-similarity.
Home-page: https://github.com/PantherLab/v2d-cli
Author: José Ignacion Escribano & Miguel Hernández & Alfonso Muñoz
Author-email: douncoge@gmail.com
License: MIT
Platform: UNKNOWN
Classifier: Environment :: Console
Classifier: Intended Audience :: System Administrators
Classifier: Intended Audience :: Other Audience
Classifier: License :: OSI Approved :: BSD License
Classifier: Operating System :: MacOS
Classifier: Operating System :: Microsoft :: Windows
Classifier: Operating System :: POSIX
Classifier: Programming Language :: Python :: 3
Requires-Python: >3.5.0
Provides-Extra: dev
